open_py_kit/__init__.py
open_py_kit/logger/__init__.py
open_py_kit/logger/config.py
open_py_kit/logger/factory.py
open_py_kit/logger/field.py
open_py_kit/logger/interface.py
open_py_kit/logger/levels.py
open_py_kit/logger/logger.py
open_py_kit/logger/nop.py
open_py_kit-0.1.2.dist-info/licenses/LICENSE
open_py_kit-0.1.2.dist-info/METADATA
open_py_kit-0.1.2.dist-info/WHEEL
open_py_kit-0.1.2.dist-info/top_level.txt
open_py_kit-0.1.2.dist-info/RECORD
